README.md
setup.py
twsyncer/__init__.py
twsyncer/config.py
twsyncer/ghub.py
twsyncer/main.py
twsyncer/twarrior.py
twsyncer/worker.py
twsyncer.egg-info/PKG-INFO
twsyncer.egg-info/SOURCES.txt
twsyncer.egg-info/dependency_links.txt
twsyncer.egg-info/entry_points.txt
twsyncer.egg-info/top_level.txt