Metadata-Version: 2.1
Name: twsyncer
Version: 0.0.4
Summary: Tool to sync Taswarrior and remote task trackers
Home-page: https://github.com/pypa/twsyncer
Author: Stan Bogatkin
Author-email: sbog@sbog.ru
License: UNKNOWN
Platform: UNKNOWN
Classifier: Programming Language :: Python :: 3
Classifier: License :: OSI Approved :: Apache Software License
Classifier: Operating System :: OS Independent
Requires-Python: >=3.6
